slogit/__init__.py
slogit/config.py
slogit/constants.py
slogit/formatters.py
slogit/handlers.py
slogit/levels.py
slogit/logger.py
slogit/models.py
slogit/py.typed
slogit-0.1.2.dist-info/METADATA
slogit-0.1.2.dist-info/WHEEL
slogit-0.1.2.dist-info/licenses/LICENSE
slogit-0.1.2.dist-info/RECORD
