Metadata-Version: 2.4
Name: slogit
Version: 0.1.2
Summary: Slogit is a logging library for Python that makes structured, configurable logging simple and intuitive.
Project-URL: Homepage, https://github.com/89jobrien/slogit
Project-URL: Repository, https://github.com/89jobrien/slogit
Author-email: jprobrien <98370624+89jobrien@users.noreply.github.com>
License: MIT
License-File: LICENSE
Classifier: Development Status :: 4 - Beta
Classifier: Intended Audience :: Developers
Classifier: License :: OSI Approved :: MIT License
Classifier: Programming Language :: Python :: 3
Classifier: Programming Language :: Python :: 3.11
Classifier: Programming Language :: Python :: 3.12
Classifier: Topic :: System :: Logging
Requires-Python: >=3.11
Requires-Dist: colorama>=0.4.6
Requires-Dist: pydantic>=2.11.7
